{
  "year": 2026,
  "round": 1,
  "name": "Australian Grand Prix",
  "laps": 58,
  "drivers": [
    {
      "driver": "RUS",
      "expected_position": 2.3,
      "median_position": 1,
      "std_position": 4.67,
      "win_pct": 86.5,
      "podium_pct": 93.2,
      "points_pct": 93.2,
      "dnf_pct": 0.0,
      "expected_points": 22.84,
      "p5_position": 1,
      "p95_position": 19,
      "actual": 1
    },
    {
      "driver": "ANT",
      "expected_position": 3.1,
      "median_position": 2,
      "std_position": 4.52,
      "win_pct": 12.9,
      "podium_pct": 93.1,
      "points_pct": 93.2,
      "dnf_pct": 0.0,
      "expected_points": 17.61,
      "p5_position": 1,
      "p95_position": 19,
      "actual": 2
    },
    {
      "driver": "HAD",
      "expected_position": 4.3,
      "median_position": 3,
      "std_position": 4.32,
      "win_pct": 0.4,
      "podium_pct": 73.8,
      "points_pct": 93.0,
      "dnf_pct": 0.0,
      "expected_points": 13.72,
      "p5_position": 2,
      "p95_position": 19,
      "actual": 20
    },
    {
      "driver": "LEC",
      "expected_position": 4.8,
      "median_position": 4,
      "std_position": 4.17,
      "win_pct": 0.1,
      "podium_pct": 35.0,
      "points_pct": 93.1,
      "dnf_pct": 0.0,
      "expected_points": 12.21,
      "p5_position": 3,
      "p95_position": 19,
      "actual": 3
    },
    {
      "driver": "PIA",
      "expected_position": 6.0,
      "median_position": 5,
      "std_position": 3.93,
      "win_pct": 0.0,
      "podium_pct": 3.7,
      "points_pct": 93.0,
      "dnf_pct": 0.0,
      "expected_points": 9.53,
      "p5_position": 4,
      "p95_position": 19,
      "actual": 21
    },
    {
      "driver": "NOR",
      "expected_position": 6.4,
      "median_position": 6,
      "std_position": 3.7,
      "win_pct": 0.0,
      "podium_pct": 1.2,
      "points_pct": 93.3,
      "dnf_pct": 0.0,
      "expected_points": 8.59,
      "p5_position": 4,
      "p95_position": 19,
      "actual": 5
    },
    {
      "driver": "HAM",
      "expected_position": 7.5,
      "median_position": 7,
      "std_position": 3.42,
      "win_pct": 0.0,
      "podium_pct": 0.0,
      "points_pct": 93.4,
      "dnf_pct": 0.0,
      "expected_points": 6.37,
      "p5_position": 5,
      "p95_position": 20,
      "actual": 4
    },
    {
      "driver": "LAW",
      "expected_position": 8.6,
      "median_position": 8,
      "std_position": 3.32,
      "win_pct": 0.0,
      "podium_pct": 0.0,
      "points_pct": 92.6,
      "dnf_pct": 0.0,
      "expected_points": 4.37,
      "p5_position": 6,
      "p95_position": 20,
      "actual": 13
    },
    {
      "driver": "HUL",
      "expected_position": 9.6,
      "median_position": 9,
      "std_position": 3.03,
      "win_pct": 0.0,
      "podium_pct": 0.0,
      "points_pct": 87.1,
      "dnf_pct": 0.0,
      "expected_points": 2.42,
      "p5_position": 7,
      "p95_position": 20,
      "actual": 22
    },
    {
      "driver": "VER",
      "expected_position": 10.1,
      "median_position": 9,
      "std_position": 3.03,
      "win_pct": 0.0,
      "podium_pct": 0.0,
      "points_pct": 80.6,
      "dnf_pct": 0.0,
      "expected_points": 1.88,
      "p5_position": 7,
      "p95_position": 20,
      "actual": 6
    },
    {
      "driver": "BOR",
      "expected_position": 10.8,
      "median_position": 10,
      "std_position": 2.88,
      "win_pct": 0.0,
      "podium_pct": 0.0,
      "points_pct": 56.2,
      "dnf_pct": 0.0,
      "expected_points": 1.02,
      "p5_position": 8,
      "p95_position": 20,
      "actual": 9
    },
    {
      "driver": "BEA",
      "expected_position": 12.0,
      "median_position": 11,
      "std_position": 2.66,
      "win_pct": 0.0,
      "podium_pct": 0.0,
      "points_pct": 21.2,
      "dnf_pct": 0.0,
      "expected_points": 0.31,
      "p5_position": 9,
      "p95_position": 20,
      "actual": 7
    },
    {
      "driver": "OCO",
      "expected_position": 12.9,
      "median_position": 12,
      "std_position": 2.4,
      "win_pct": 0.0,
      "podium_pct": 0.0,
      "points_pct": 7.0,
      "dnf_pct": 0.0,
      "expected_points": 0.09,
      "p5_position": 10,
      "p95_position": 20,
      "actual": 11
    },
    {
      "driver": "PER",
      "expected_position": 14.3,
      "median_position": 14,
      "std_position": 2.23,
      "win_pct": 0.0,
      "podium_pct": 0.0,
      "points_pct": 1.2,
      "dnf_pct": 0.0,
      "expected_points": 0.01,
      "p5_position": 11,
      "p95_position": 20,
      "actual": 16
    },
    {
      "driver": "ALB",
      "expected_position": 14.4,
      "median_position": 14,
      "std_position": 2.27,
      "win_pct": 0.0,
      "podium_pct": 0.0,
      "points_pct": 1.2,
      "dnf_pct": 0.0,
      "expected_points": 0.02,
      "p5_position": 11,
      "p95_position": 20,
      "actual": 12
    },
    {
      "driver": "ALO",
      "expected_position": 14.7,
      "median_position": 14,
      "std_position": 2.17,
      "win_pct": 0.0,
      "podium_pct": 0.0,
      "points_pct": 0.7,
      "dnf_pct": 0.0,
      "expected_points": 0.01,
      "p5_position": 12,
      "p95_position": 20,
      "actual": 18
    },
    {
      "driver": "BOT",
      "expected_position": 16.4,
      "median_position": 16,
      "std_position": 1.84,
      "win_pct": 0.0,
      "podium_pct": 0.0,
      "points_pct": 0.1,
      "dnf_pct": 0.0,
      "expected_points": 0.0,
      "p5_position": 14,
      "p95_position": 21,
      "actual": 19
    },
    {
      "driver": "GAS",
      "expected_position": 17.1,
      "median_position": 17,
      "std_position": 1.68,
      "win_pct": 0.0,
      "podium_pct": 0.0,
      "points_pct": 0.0,
      "dnf_pct": 0.0,
      "expected_points": 0.0,
      "p5_position": 14,
      "p95_position": 21,
      "actual": 10
    },
    {
      "driver": "COL",
      "expected_position": 17.5,
      "median_position": 18,
      "std_position": 1.62,
      "win_pct": 0.0,
      "podium_pct": 0.0,
      "points_pct": 0.0,
      "dnf_pct": 0.0,
      "expected_points": 0.0,
      "p5_position": 15,
      "p95_position": 21,
      "actual": 14
    },
    {
      "driver": "SAI",
      "expected_position": 18.6,
      "median_position": 19,
      "std_position": 1.32,
      "win_pct": 0.0,
      "podium_pct": 0.0,
      "points_pct": 0.0,
      "dnf_pct": 0.0,
      "expected_points": 0.0,
      "p5_position": 16,
      "p95_position": 21,
      "actual": 15
    },
    {
      "driver": "STR",
      "expected_position": 19.7,
      "median_position": 20,
      "std_position": 1.15,
      "win_pct": 0.0,
      "podium_pct": 0.0,
      "points_pct": 0.0,
      "dnf_pct": 0.0,
      "expected_points": 0.0,
      "p5_position": 18,
      "p95_position": 21,
      "actual": 17
    }
  ],
  "mode": "official"
}
