{
  "year": 2020,
  "round": 17,
  "name": "Abu Dhabi Grand Prix",
  "laps": 55,
  "drivers": [
    {
      "driver": "BOT",
      "expected_position": 2.7,
      "median_position": 2,
      "std_position": 4.02,
      "win_pct": 41.4,
      "podium_pct": 94.4,
      "points_pct": 94.4,
      "dnf_pct": 0.0,
      "expected_points": 19.29,
      "p5_position": 1,
      "p95_position": 18,
      "actual": 2
    },
    {
      "driver": "VER",
      "expected_position": 2.7,
      "median_position": 2,
      "std_position": 3.91,
      "win_pct": 38.8,
      "podium_pct": 94.8,
      "points_pct": 94.8,
      "dnf_pct": 0.0,
      "expected_points": 19.12,
      "p5_position": 1,
      "p95_position": 17,
      "actual": 1
    },
    {
      "driver": "HAM",
      "expected_position": 3.2,
      "median_position": 2,
      "std_position": 3.89,
      "win_pct": 19.8,
      "podium_pct": 94.5,
      "points_pct": 94.6,
      "dnf_pct": 0.0,
      "expected_points": 17.13,
      "p5_position": 1,
      "p95_position": 18,
      "actual": 3
    },
    {
      "driver": "ALB",
      "expected_position": 5.1,
      "median_position": 4,
      "std_position": 3.36,
      "win_pct": 0.0,
      "podium_pct": 7.8,
      "points_pct": 94.8,
      "dnf_pct": 0.0,
      "expected_points": 10.83,
      "p5_position": 3,
      "p95_position": 17,
      "actual": 4
    },
    {
      "driver": "NOR",
      "expected_position": 5.1,
      "median_position": 4,
      "std_position": 3.35,
      "win_pct": 0.0,
      "podium_pct": 8.2,
      "points_pct": 94.9,
      "dnf_pct": 0.0,
      "expected_points": 10.84,
      "p5_position": 3,
      "p95_position": 17,
      "actual": 5
    },
    {
      "driver": "SAI",
      "expected_position": 6.5,
      "median_position": 6,
      "std_position": 3.11,
      "win_pct": 0.0,
      "podium_pct": 0.2,
      "points_pct": 94.6,
      "dnf_pct": 0.0,
      "expected_points": 8.05,
      "p5_position": 5,
      "p95_position": 18,
      "actual": 6
    },
    {
      "driver": "KVY",
      "expected_position": 7.8,
      "median_position": 7,
      "std_position": 2.88,
      "win_pct": 0.0,
      "podium_pct": 0.0,
      "points_pct": 94.6,
      "dnf_pct": 0.0,
      "expected_points": 5.48,
      "p5_position": 6,
      "p95_position": 18,
      "actual": 11
    },
    {
      "driver": "STR",
      "expected_position": 8.0,
      "median_position": 7,
      "std_position": 2.81,
      "win_pct": 0.0,
      "podium_pct": 0.0,
      "points_pct": 94.7,
      "dnf_pct": 0.0,
      "expected_points": 5.07,
      "p5_position": 6,
      "p95_position": 18,
      "actual": 10
    },
    {
      "driver": "GAS",
      "expected_position": 9.3,
      "median_position": 9,
      "std_position": 2.66,
      "win_pct": 0.0,
      "podium_pct": 0.0,
      "points_pct": 90.2,
      "dnf_pct": 0.0,
      "expected_points": 2.67,
      "p5_position": 7,
      "p95_position": 18,
      "actual": 8
    },
    {
      "driver": "OCO",
      "expected_position": 10.9,
      "median_position": 10,
      "std_position": 2.5,
      "win_pct": 0.0,
      "podium_pct": 0.0,
      "points_pct": 55.5,
      "dnf_pct": 0.0,
      "expected_points": 0.98,
      "p5_position": 8,
      "p95_position": 19,
      "actual": 9
    },
    {
      "driver": "VET",
      "expected_position": 11.3,
      "median_position": 11,
      "std_position": 2.45,
      "win_pct": 0.0,
      "podium_pct": 0.0,
      "points_pct": 40.7,
      "dnf_pct": 0.0,
      "expected_points": 0.67,
      "p5_position": 9,
      "p95_position": 19,
      "actual": 14
    },
    {
      "driver": "PER",
      "expected_position": 11.9,
      "median_position": 12,
      "std_position": 2.38,
      "win_pct": 0.0,
      "podium_pct": 0.0,
      "points_pct": 25.4,
      "dnf_pct": 0.0,
      "expected_points": 0.4,
      "p5_position": 9,
      "p95_position": 19,
      "actual": 20
    },
    {
      "driver": "RIC",
      "expected_position": 11.9,
      "median_position": 12,
      "std_position": 2.29,
      "win_pct": 0.0,
      "podium_pct": 0.0,
      "points_pct": 25.2,
      "dnf_pct": 0.0,
      "expected_points": 0.39,
      "p5_position": 9,
      "p95_position": 15,
      "actual": 7
    },
    {
      "driver": "LEC",
      "expected_position": 13.2,
      "median_position": 13,
      "std_position": 1.99,
      "win_pct": 0.0,
      "podium_pct": 0.0,
      "points_pct": 5.1,
      "dnf_pct": 0.0,
      "expected_points": 0.07,
      "p5_position": 10,
      "p95_position": 18,
      "actual": 13
    },
    {
      "driver": "RAI",
      "expected_position": 14.5,
      "median_position": 14,
      "std_position": 1.65,
      "win_pct": 0.0,
      "podium_pct": 0.0,
      "points_pct": 0.4,
      "dnf_pct": 0.0,
      "expected_points": 0.0,
      "p5_position": 12,
      "p95_position": 19,
      "actual": 12
    },
    {
      "driver": "GIO",
      "expected_position": 16.1,
      "median_position": 16,
      "std_position": 1.58,
      "win_pct": 0.0,
      "podium_pct": 0.0,
      "points_pct": 0.0,
      "dnf_pct": 0.0,
      "expected_points": 0.0,
      "p5_position": 14,
      "p95_position": 19,
      "actual": 16
    },
    {
      "driver": "RUS",
      "expected_position": 16.4,
      "median_position": 16,
      "std_position": 1.55,
      "win_pct": 0.0,
      "podium_pct": 0.0,
      "points_pct": 0.0,
      "dnf_pct": 0.0,
      "expected_points": 0.0,
      "p5_position": 14,
      "p95_position": 19,
      "actual": 15
    },
    {
      "driver": "FIT",
      "expected_position": 16.6,
      "median_position": 17,
      "std_position": 1.52,
      "win_pct": 0.0,
      "podium_pct": 0.0,
      "points_pct": 0.0,
      "dnf_pct": 0.0,
      "expected_points": 0.0,
      "p5_position": 14,
      "p95_position": 19,
      "actual": 19
    },
    {
      "driver": "LAT",
      "expected_position": 17.8,
      "median_position": 18,
      "std_position": 1.24,
      "win_pct": 0.0,
      "podium_pct": 0.0,
      "points_pct": 0.0,
      "dnf_pct": 0.0,
      "expected_points": 0.0,
      "p5_position": 16,
      "p95_position": 20,
      "actual": 17
    },
    {
      "driver": "MAG",
      "expected_position": 19.0,
      "median_position": 19,
      "std_position": 0.99,
      "win_pct": 0.0,
      "podium_pct": 0.0,
      "points_pct": 0.0,
      "dnf_pct": 0.0,
      "expected_points": 0.0,
      "p5_position": 17,
      "p95_position": 20,
      "actual": 18
    }
  ],
  "mode": "official"
}
