{
  "year": 2023,
  "round": 13,
  "name": "Dutch Grand Prix",
  "laps": 72,
  "mode": "official",
  "drivers": [
    {
      "driver": "VER",
      "expected_position": 1.5,
      "median_position": 1,
      "std_position": 2.62,
      "win_pct": 95.7,
      "podium_pct": 96.7,
      "points_pct": 96.7,
      "dnf_pct": 3.3,
      "expected_points": 24.1,
      "p5_position": 1,
      "p95_position": 1,
      "actual": 1.0
    },
    {
      "driver": "RUS",
      "expected_position": 4.1,
      "median_position": 3,
      "std_position": 4.37,
      "win_pct": 1.4,
      "podium_pct": 87.9,
      "points_pct": 88.0,
      "dnf_pct": 12.0,
      "expected_points": 14.55,
      "p5_position": 2,
      "p95_position": 16,
      "actual": 17.0
    },
    {
      "driver": "ALO",
      "expected_position": 4.5,
      "median_position": 4,
      "std_position": 2.67,
      "win_pct": 0.1,
      "podium_pct": 22.8,
      "points_pct": 95.3,
      "dnf_pct": 4.7,
      "expected_points": 11.71,
      "p5_position": 3,
      "p95_position": 7,
      "actual": 2.0
    },
    {
      "driver": "NOR",
      "expected_position": 4.8,
      "median_position": 2,
      "std_position": 5.31,
      "win_pct": 2.8,
      "podium_pct": 81.4,
      "points_pct": 81.4,
      "dnf_pct": 18.6,
      "expected_points": 14.16,
      "p5_position": 2,
      "p95_position": 17,
      "actual": 7.0
    },
    {
      "driver": "PER",
      "expected_position": 6.1,
      "median_position": 5,
      "std_position": 2.88,
      "win_pct": 0.0,
      "podium_pct": 4.0,
      "points_pct": 93.5,
      "dnf_pct": 6.5,
      "expected_points": 8.71,
      "p5_position": 4,
      "p95_position": 15,
      "actual": 4.0
    },
    {
      "driver": "SAI",
      "expected_position": 6.5,
      "median_position": 6,
      "std_position": 3.11,
      "win_pct": 0.0,
      "podium_pct": 2.6,
      "points_pct": 91.8,
      "dnf_pct": 8.2,
      "expected_points": 8.05,
      "p5_position": 4,
      "p95_position": 16,
      "actual": 5.0
    },
    {
      "driver": "HAM",
      "expected_position": 8.3,
      "median_position": 8,
      "std_position": 2.2,
      "win_pct": 0.0,
      "podium_pct": 0.0,
      "points_pct": 93.9,
      "dnf_pct": 4.6,
      "expected_points": 4.07,
      "p5_position": 6,
      "p95_position": 11,
      "actual": 6.0
    },
    {
      "driver": "ALB",
      "expected_position": 8.5,
      "median_position": 6,
      "std_position": 5.28,
      "win_pct": 0.0,
      "podium_pct": 4.5,
      "points_pct": 69.1,
      "dnf_pct": 30.9,
      "expected_points": 6.83,
      "p5_position": 4,
      "p95_position": 18,
      "actual": 8.0
    },
    {
      "driver": "LEC",
      "expected_position": 8.8,
      "median_position": 8,
      "std_position": 2.68,
      "win_pct": 0.0,
      "podium_pct": 0.0,
      "points_pct": 89.4,
      "dnf_pct": 8.6,
      "expected_points": 3.65,
      "p5_position": 6,
      "p95_position": 16,
      "actual": 19.0
    },
    {
      "driver": "STR",
      "expected_position": 10.4,
      "median_position": 10,
      "std_position": 2.63,
      "win_pct": 0.0,
      "podium_pct": 0.0,
      "points_pct": 70.7,
      "dnf_pct": 11.9,
      "expected_points": 1.57,
      "p5_position": 8,
      "p95_position": 17,
      "actual": 11.0
    },
    {
      "driver": "PIA",
      "expected_position": 10.6,
      "median_position": 9,
      "std_position": 4.01,
      "win_pct": 0.0,
      "podium_pct": 0.0,
      "points_pct": 70.1,
      "dnf_pct": 27.9,
      "expected_points": 2.72,
      "p5_position": 6,
      "p95_position": 18,
      "actual": 9.0
    },
    {
      "driver": "GAS",
      "expected_position": 12.5,
      "median_position": 12,
      "std_position": 2.75,
      "win_pct": 0.0,
      "podium_pct": 0.0,
      "points_pct": 21.6,
      "dnf_pct": 21.2,
      "expected_points": 0.31,
      "p5_position": 9,
      "p95_position": 18,
      "actual": 3.0
    },
    {
      "driver": "MAG",
      "expected_position": 12.8,
      "median_position": 12,
      "std_position": 3.14,
      "win_pct": 0.0,
      "podium_pct": 0.0,
      "points_pct": 25.1,
      "dnf_pct": 30.4,
      "expected_points": 0.38,
      "p5_position": 9,
      "p95_position": 18,
      "actual": 16.0
    },
    {
      "driver": "OCO",
      "expected_position": 13.8,
      "median_position": 13,
      "std_position": 2.57,
      "win_pct": 0.0,
      "podium_pct": 0.0,
      "points_pct": 5.1,
      "dnf_pct": 23.9,
      "expected_points": 0.07,
      "p5_position": 10,
      "p95_position": 19,
      "actual": 10.0
    },
    {
      "driver": "SAR",
      "expected_position": 14.1,
      "median_position": 13,
      "std_position": 2.74,
      "win_pct": 0.0,
      "podium_pct": 0.0,
      "points_pct": 5.5,
      "dnf_pct": 30.3,
      "expected_points": 0.07,
      "p5_position": 10,
      "p95_position": 19,
      "actual": 20.0
    },
    {
      "driver": "HUL",
      "expected_position": 15.3,
      "median_position": 15,
      "std_position": 2.43,
      "win_pct": 0.0,
      "podium_pct": 0.0,
      "points_pct": 1.2,
      "dnf_pct": 30.1,
      "expected_points": 0.01,
      "p5_position": 12,
      "p95_position": 19,
      "actual": 12.0
    },
    {
      "driver": "ZHO",
      "expected_position": 15.4,
      "median_position": 15,
      "std_position": 2.4,
      "win_pct": 0.0,
      "podium_pct": 0.0,
      "points_pct": 1.0,
      "dnf_pct": 29.9,
      "expected_points": 0.01,
      "p5_position": 12,
      "p95_position": 19,
      "actual": 18.0
    },
    {
      "driver": "TSU",
      "expected_position": 15.9,
      "median_position": 16,
      "std_position": 2.15,
      "win_pct": 0.0,
      "podium_pct": 0.0,
      "points_pct": 0.3,
      "dnf_pct": 23.5,
      "expected_points": 0.0,
      "p5_position": 12,
      "p95_position": 19,
      "actual": 15.0
    },
    {
      "driver": "BOT",
      "expected_position": 16.2,
      "median_position": 16,
      "std_position": 2.18,
      "win_pct": 0.0,
      "podium_pct": 0.0,
      "points_pct": 0.2,
      "dnf_pct": 29.7,
      "expected_points": 0.0,
      "p5_position": 13,
      "p95_position": 19,
      "actual": 14.0
    }
  ]
}